stylinator/__init__.py
vistside/__init__.py
vistside/core/__init__.py
vistside/core/_align_enum.py
vistside/core/_array_field.py
vistside/core/_brush_factory.py
vistside/core/_brush_field.py
vistside/core/_color_factory.py
vistside/core/_colors.py
vistside/core/_data_roll.py
vistside/core/_empty_brush.py
vistside/core/_empty_pen.py
vistside/core/_font_factory.py
vistside/core/_font_field.py
vistside/core/_font_pen_field.py
vistside/core/_keyboard_shortcuts.py
vistside/core/_parse_parent.py
vistside/core/_pen_factory.py
vistside/core/_pen_field.py
vistside/core/_qt_enums.py
vistside/core/_right_now_field.py
vistside/core/_text_pen.py
vistside/core/_timer_factory.py
vistside/core/_timer_field.py
vistside/core/_white_noisinator.py
vistside/core/icons/__init__.py
vistside/core/icons/_get_icon.py
vistside/core/icons/icons.py
vistside/paint/__init__.py
vistside/paint/_abstract_paint.py
vistside/paint/_border_rect.py
vistside/paint/_data_paint.py
vistside/paint/_fill_rect.py
vistside/paint/_text_rect.py
vistside/widgets/__init__.py
vistside/widgets/_abstract_dialog_field.py
vistside/widgets/_base_layout_field.py
vistside/widgets/_base_widget.py
vistside/widgets/_clock_widget.py
vistside/widgets/_confirm_dialog.py
vistside/widgets/_dynamic_plot_widget.py
vistside/widgets/_fill_widget.py
vistside/widgets/_grid_layout.py
vistside/widgets/_horizontal_layout.py
vistside/widgets/_jk_flip_flop.py
vistside/widgets/_label_widget.py
vistside/widgets/_lcd_field.py
vistside/widgets/_mouse_aware.py
vistside/widgets/_plot_widget.py
vistside/widgets/_quick_field.py
vistside/widgets/_safety_toggle_button.py
vistside/widgets/_vertical_layout.py
vistside/windows/__init__.py
vistside/windows/_base_window.py
vistside/windows/_layout_window.py
vistside/windows/actions/__init__.py
vistside/windows/actions/_abstract_menu.py
vistside/windows/actions/_debug_menu.py
vistside/windows/actions/_edit_menu.py
vistside/windows/actions/_files_menu.py
vistside/windows/actions/_help_menu.py
vistside-0.1.28.dist-info/LICENSE
vistside-0.1.28.dist-info/METADATA
vistside-0.1.28.dist-info/WHEEL
vistside-0.1.28.dist-info/top_level.txt
vistside-0.1.28.dist-info/RECORD
