Metadata-Version: 2.1
Name: vistside
Version: 0.1.28
Summary: vistside expands vistutils with utilities for PySide6
Home-page: https://github.com/AsgerJon/vistside
Author: Asger Jon Vistisen
Author-email: Asger Jon Vistisen <asgerjon2@gmail.com>
Project-URL: Homepage, https://github.com/AsgerJon/vistside
Project-URL: Bug Tracker, https://github.com/AsgerJon/vistside
Classifier: Programming Language :: Python :: 3
Classifier: License :: OSI Approved :: MIT License
Classifier: Operating System :: OS Independent
Requires-Python: >=3.11
License-File: LICENSE
